count_in_list/__init__.py
counter/__init__.py
test_package/__init__.py
count_in_list-0.0.4.dist-info/METADATA
count_in_list-0.0.4.dist-info/WHEEL
count_in_list-0.0.4.dist-info/top_level.txt
count_in_list-0.0.4.dist-info/RECORD
