Metadata-Version: 2.1
Name: count-in-list
Version: 0.0.4
Summary: A sample test package
Home-page: https://github.com/khalidjshaikh/count_in_list
Author: Khalid Shaikh
Author-email: k@ruby.run
License: MIT
Requires-Python: >=3.8
